internationalization/__init__.py
internationalization/exceptions.py
internationalization/internationalization.py
internationalization/language.py
internationalization/loaders/__init__.py
internationalization/loaders/base_loader.py
internationalization/loaders/files_pack.py
internationalization/loaders/yaml.py
internationalization/singleton.py
internationalization/types/__init__.py
internationalization/types/full_language.py
internationalization/types/language_phrase.py
internationalization/types/path_file.py
internationalization/types/phrase.py
internationalization_py-0.1.4.dist-info/LICENSE
internationalization_py-0.1.4.dist-info/METADATA
internationalization_py-0.1.4.dist-info/WHEEL
internationalization_py-0.1.4.dist-info/RECORD
