Metadata-Version: 2.1
Name: internationalization-py
Version: 0.1.4
Summary: Internationalization library for comfortable usage
Home-page: https://github.com/cortelf/internationalization.py
License: MIT
Author: CortelF
Requires-Python: >=3.7,<4.0
Classifier: Development Status :: 4 - Beta
Classifier: Environment :: Console
Classifier: Intended Audience :: Developers
Classifier: License :: OSI Approved :: MIT License
Classifier: Programming Language :: Python :: 3
Classifier: Programming Language :: Python :: 3.7
Classifier: Programming Language :: Python :: 3.8
Classifier: Programming Language :: Python :: 3.9
Classifier: Programming Language :: Python :: 3.10
Classifier: Programming Language :: Python :: 3.11
Classifier: Programming Language :: Python :: 3
Classifier: Programming Language :: Python :: 3.10
Classifier: Programming Language :: Python :: 3.11
Classifier: Programming Language :: Python :: 3.7
Classifier: Programming Language :: Python :: 3.8
Classifier: Programming Language :: Python :: 3.9
Classifier: Topic :: Software Development :: Libraries
Requires-Dist: pydantic (>=1.8)
Requires-Dist: pyyaml (>=5.0)
Project-URL: Bug Tracker, https://github.com/cortelf/internationalization.py/issues
Project-URL: Repository, https://github.com/cortelf/internationalization.py
